KFSdropbox/KFSdropbox.py
kfsdropbox-1.0.2.dist-info/METADATA
kfsdropbox-1.0.2.dist-info/WHEEL
kfsdropbox-1.0.2.dist-info/RECORD
